ai_traineree/__init__.py
ai_traineree/noise.py
ai_traineree/policies.py
ai_traineree/tasks.py
ai_traineree/utils.py
ai_traineree/agents/__init__.py
ai_traineree/agents/agent_factory.py
ai_traineree/agents/agent_utils.py
ai_traineree/agents/d3pg.py
ai_traineree/agents/d4pg.py
ai_traineree/agents/ddpg.py
ai_traineree/agents/dqn.py
ai_traineree/agents/dummy.py
ai_traineree/agents/ppo.py
ai_traineree/agents/rainbow.py
ai_traineree/agents/sac.py
ai_traineree/agents/td3.py
ai_traineree/buffers/__init__.py
ai_traineree/buffers/buffer_factory.py
ai_traineree/buffers/nstep.py
ai_traineree/buffers/per.py
ai_traineree/buffers/replay.py
ai_traineree/buffers/rollout.py
ai_traineree/loggers/__init__.py
ai_traineree/loggers/data_logger.py
ai_traineree/loggers/file_logger.py
ai_traineree/loggers/neptune_logger.py
ai_traineree/loggers/tensorboard_logger.py
ai_traineree/multi_agents/__init__.py
ai_traineree/multi_agents/independent.py
ai_traineree/multi_agents/iql.py
ai_traineree/multi_agents/maddpg.py
ai_traineree/networks/__init__.py
ai_traineree/networks/bodies.py
ai_traineree/networks/heads.py
ai_traineree/runners/__init__.py
ai_traineree/runners/env_runner.py
ai_traineree/runners/multi_sync_env_runner.py
ai_traineree/runners/multiagent_env_runner.py
ai_traineree/types/__init__.py
ai_traineree/types/agent.py
ai_traineree/types/dataspace.py
ai_traineree/types/experience.py
ai_traineree/types/primitive.py
ai_traineree/types/state.py
ai_traineree/types/task.py
ai_traineree-0.7.1.dist-info/METADATA
ai_traineree-0.7.1.dist-info/WHEEL
ai_traineree-0.7.1.dist-info/licenses/LICENSE.txt
ai_traineree-0.7.1.dist-info/RECORD
