Metadata-Version: 2.4
Name: ai-traineree
Version: 0.7.1
Summary: Yet another zoo of (Deep) Reinforcement Learning methods in Python using PyTorch
License-File: LICENSE.txt
Requires-Python: >=3.12
Requires-Dist: gymnasium==1.0.0
Requires-Dist: jsons>=1.4
Requires-Dist: matplotlib>=3.7.5
Requires-Dist: numpy>=2.0
Requires-Dist: torch>=2.0
Provides-Extra: examples
Requires-Dist: gymnasium==1.0.0; extra == 'examples'
Requires-Dist: matplotlib; extra == 'examples'
Requires-Dist: tensorboard; extra == 'examples'
Provides-Extra: gym
Requires-Dist: gymnasium[all]==1.0.0; extra == 'gym'
Provides-Extra: neptune
Requires-Dist: neptune-client; extra == 'neptune'
Requires-Dist: psutil; extra == 'neptune'
Provides-Extra: plot
Requires-Dist: matplotlib; extra == 'plot'
Provides-Extra: tensorboard
Requires-Dist: tensorboard; extra == 'tensorboard'
